MANIFEST.in
README.rst
requirements-tests.txt
setup.cfg
setup.py
django_volatile_messages.egg-info/PKG-INFO
django_volatile_messages.egg-info/SOURCES.txt
django_volatile_messages.egg-info/dependency_links.txt
django_volatile_messages.egg-info/top_level.txt
volatile_messages/.__init__.py.swp
volatile_messages/.models.py.swp
volatile_messages/__init__.py
volatile_messages/admin.py
volatile_messages/apps.py
volatile_messages/models.py
volatile_messages/settings.py
volatile_messages/views.py
volatile_messages/migrations/0001_initial.py
volatile_messages/migrations/__init__.py
volatile_messages/templates/volatile_messages/base/__str__.html
volatile_messages/templates/volatile_messages/base/content.html
volatile_messages/templates/volatile_messages/base/message.html
volatile_messages/templatetags/.volatile_messages.py.swp
volatile_messages/templatetags/__init__.py
volatile_messages/templatetags/volatile_messages.py
volatile_messages/tests/.test_models.py.swp
volatile_messages/tests/.test_templatetags.py.swp
volatile_messages/tests/__init__.py
volatile_messages/tests/settings.py
volatile_messages/tests/test_models.py
volatile_messages/tests/test_templatetags.py
volatile_messages/tests/testapp/__init__.py
volatile_messages/tests/testapp/models.py
volatile_messages/tests/testapp/views.py
volatile_messages/tests/testapp/templates/test_template.html
volatile_messages/tests/testapp/templates/volatile_messages/foo-template.html