Metadata-Version: 1.1
Name: django-volatile-messages
Version: 0.1
Summary: Django app for create volatile message system
Home-page: https://github.com/ZuluPro/django-volatile-message
Author: Anthony Monthe (ZuluPro)
Author-email: anthony.monthe@gmail.com
License: BSD
Keywords: django,web,volatile_messages,html
Platform: UNKNOWN
Classifier: Development Status :: 4 - Beta
Classifier: Environment :: Web Environment
Classifier: Environment :: Console
Classifier: Framework :: Django
Classifier: Intended Audience :: Developers
Classifier: License :: OSI Approved :: BSD License
Classifier: Natural Language :: English
Classifier: Operating System :: OS Independent
Classifier: Programming Language :: Python
Classifier: Programming Language :: Python :: 2
Classifier: Programming Language :: Python :: 2.7
Classifier: Programming Language :: Python :: 3
Classifier: Programming Language :: Python :: 3.3
Classifier: Programming Language :: Python :: 3.4
Classifier: Programming Language :: Python :: 3.5
